MANIFEST.in
README.md
requirements.txt
setup.py
ipyvanish/__init__.py
ipyvanish/core.py
ipyvanish.egg-info/PKG-INFO
ipyvanish.egg-info/SOURCES.txt
ipyvanish.egg-info/dependency_links.txt
ipyvanish.egg-info/entry_points.txt
ipyvanish.egg-info/requires.txt
ipyvanish.egg-info/top_level.txt