Metadata-Version: 1.1
Name: ipyvanish
Version: 0.0.1
Summary: A simple python CLI for the IPVanish VPN
Home-page: https://github.com/limx0/ipyvanish
Author: Bradley McElroy
Author-email: bradley.mcelroy@live.com
License: BSD
Download-URL: https://github.com/limx0/ipyvanish/tarball/0.0.1
Platform: UNKNOWN
Classifier: Programming Language :: Python :: 3
